<?xml version="1.0" encoding="UTF-8"?><record_update table="sp_page_route_map">
    <sp_page_route_map action="INSERT_OR_UPDATE">
        <active>true</active>
        <order>9</order>
        <portals>9ec0914847630210aeb77f52d16d4346</portals>
        <route_from_page display_value="search">87466b63c3223100c8b837659bba8feb</route_from_page>
        <route_to_page display_value="ec_ai_search">d8c5bdf498fb5410f87779d8cd2ec846</route_to_page>
        <short_description>EC AI Search Page Route</short_description>
        <sys_class_name>sp_page_route_map</sys_class_name>
        <sys_created_by>admin</sys_created_by>
        <sys_created_on>2024-07-17 10:00:26</sys_created_on>
        <sys_id>fec0d14847630210aeb77f52d16d43b5</sys_id>
        <sys_mod_count>0</sys_mod_count>
        <sys_name>87466b63c3223100c8b837659bba8feb</sys_name>
        <sys_package display_value="Travel Request" source="x_1040531_travel_0">d61584f0473a4210aeb77f52d16d43bb</sys_package>
        <sys_policy/>
        <sys_scope display_value="Travel Request">d61584f0473a4210aeb77f52d16d43bb</sys_scope>
        <sys_update_name>sp_page_route_map_fec0d14847630210aeb77f52d16d43b5</sys_update_name>
        <sys_updated_by>admin</sys_updated_by>
        <sys_updated_on>2024-07-17 10:00:26</sys_updated_on>
    </sp_page_route_map>
</record_update>
